LICENSE.txt
MANIFEST.in
README.rst
setup.cfg
setup.py
knife/__init__.py
knife/active.py
knife/base.py
knife/lazy.py
knife/mixins.py
knife.egg-info/PKG-INFO
knife.egg-info/SOURCES.txt
knife.egg-info/dependency_links.txt
knife.egg-info/not-zip-safe
knife.egg-info/requires.txt
knife.egg-info/top_level.txt
reqs/requires.txt
tests/__init__.py
tests/mixins.py
tests/test_active.py
tests/test_lazy.py